poirot/__init__.py
poirot/clients.py
poirot/commands.py
poirot/filters.py
poirot/helpers.py
poirot/parser.py
poirot/poirot.py
poirot/style.py
poirot/utils.py
poirot/patterns/default.txt
poirot/templates/console.html
poirot/templates/console_thin.html
poirot-1.0.1.dist-info/DESCRIPTION.rst
poirot-1.0.1.dist-info/entry_points.txt
poirot-1.0.1.dist-info/METADATA
poirot-1.0.1.dist-info/metadata.json
poirot-1.0.1.dist-info/RECORD
poirot-1.0.1.dist-info/top_level.txt
poirot-1.0.1.dist-info/WHEEL
