Metadata-Version: 2.0
Name: poirot
Version: 1.0.1
Summary: Search a Git repository's full revision history (commit messages and diffs) for text patterns.
Home-page: https://github.com/emanuelfeld/poirot
Author: Emanuel Feld
Author-email: elefbet@gmail.com
License: https://raw.githubusercontent.com/emanuelfeld/poirot/master/LICENSE.md
Platform: UNKNOWN
Classifier: Environment :: Console
Classifier: Intended Audience :: Developers
Classifier: Development Status :: 3 - Alpha
Classifier: License :: OSI Approved :: MIT License
Classifier: Programming Language :: Python
Classifier: Programming Language :: Python :: 2.7
Classifier: Programming Language :: Python :: 3.3
Classifier: Programming Language :: Python :: 3.4
Classifier: Programming Language :: Python :: 3.5
Requires-Dist: tqdm (>=3.4.0)
Requires-Dist: Jinja2 (>=2.8)
Requires-Dist: regex (>=2015.11.22)
Requires-Dist: requests (>=2.9.1)
